LICENSE
MANIFEST.in
README.md
requirements.txt
setup.py
imgdisplay/__init__.py
imgdisplay/imgdisplay.py
imgdisplay.egg-info/PKG-INFO
imgdisplay.egg-info/SOURCES.txt
imgdisplay.egg-info/dependency_links.txt
imgdisplay.egg-info/entry_points.txt
imgdisplay.egg-info/requires.txt
imgdisplay.egg-info/top_level.txt
imgdisplay/static/styling.css
imgdisplay/templates/img.html