Metadata-Version: 1.0
Name: imgdisplay
Version: 2016.12.26.19.35
Summary: A command-line app to slideshow photos in a directory.
Home-page: https://github.com/ericmjl/imgdisplay
Author: Eric J. Ma
Author-email: ericmajinglong@gmail.com
License: Copyright 2016 Eric J. Ma
